setup.py
djangopersian/__init__.py
djangopersian/admin.py
djangopersian/apps.py
djangopersian/filters.py
djangopersian/utils.py
djangopersian/widgets.py
djangopersian.egg-info/PKG-INFO
djangopersian.egg-info/SOURCES.txt
djangopersian.egg-info/dependency_links.txt
djangopersian.egg-info/not-zip-safe
djangopersian.egg-info/top_level.txt