Metadata-Version: 1.0
Name: djangopersian
Version: 0.1.0rc1
Summary: Drop-in persian (farsi) localization for Django projects, including jalali date widgets and admin utilities
Home-page: https://github.com/amiraliakbari/djangopersian
Author: AmirAli Akbari
Author-email: amiraliakbari@gmail.com
License: MIT
Platform: UNKNOWN
